setup.cfg
setup.py
s3_nexrad_search/__init__.py
s3_nexrad_search/s3_nexrad_search.py
s3_nexrad_search.egg-info/PKG-INFO
s3_nexrad_search.egg-info/SOURCES.txt
s3_nexrad_search.egg-info/dependency_links.txt
s3_nexrad_search.egg-info/not-zip-safe
s3_nexrad_search.egg-info/requires.txt
s3_nexrad_search.egg-info/top_level.txt
scripts/nexrad_get