Metadata-Version: 1.1
Name: s3-nexrad-search
Version: 1.1
Summary: Command line utility and Python library to search the NEXRAD Level II dataset hosted in Amazon's S3
Home-page: https://github.com/stephenlienharrell/S3-NEXRAD-Search
Author: Stephen Lien Harrell
Author-email: stephen@teknikal.org
License: MIT
Download-URL: https://github.com/stephenlienharrell/S3-NEXRAD-Search/archive/1.1.tar.gz
Keywords: radar,NEXRAD,AWS,S3,longitude,latitude
Platform: UNKNOWN
Classifier: Programming Language :: Python :: 2.7
